nagao/__init__.py
nagao/__main__.py
nagao/nagao.py
nagao/utils.py
nagao/data/punct.txt
nagao/data/stopwords_en.txt
nagao/data/stopwords_zh.txt
nagao-0.1.1.data/scripts/nagao
nagao-0.1.1.dist-info/LICENSE.txt
nagao-0.1.1.dist-info/METADATA
nagao-0.1.1.dist-info/WHEEL
nagao-0.1.1.dist-info/top_level.txt
nagao-0.1.1.dist-info/RECORD
