Metadata-Version: 2.1
Name: nagao
Version: 0.1.1
Summary: Counting word frequency based on Nagao algorithm
Home-page: https://github.com/Chiang97912/nagao
Author: Chiang97912
Author-email: chiang97912@gmail.com
License: UNKNOWN
Keywords: nagao
Platform: UNKNOWN
Classifier: Development Status :: 3 - Alpha
Classifier: Intended Audience :: Developers
Classifier: License :: OSI Approved :: MIT License
Classifier: Programming Language :: Python :: 3.6
License-File: LICENSE.txt
Requires-Dist: click (>=7.1.2)
Requires-Dist: nltk (>=3.5)
Requires-Dist: sqlite-utils (>=3.26.1)
Requires-Dist: ext-sort (>=0.2.0)
